semantic_counter/__init__.py
semantic_counter/semantic_vectorizer.py
semantic_counter-0.0.4.dist-info/METADATA
semantic_counter-0.0.4.dist-info/WHEEL
semantic_counter-0.0.4.dist-info/licenses/LICENSE
semantic_counter-0.0.4.dist-info/RECORD
