Metadata-Version: 2.1
Name: semantic_counter
Version: 0.0.4
Summary: A wrapper around CountVectorizer which counts semantically similar tokens
Project-URL: Homepage, https://github.com/deepakdalakoti/SemanticVectorizer
Project-URL: Bug Tracker, https://github.com/deepakdalakoti/SemanticVectorizer/issues
Author-email: Deepak Dalakoti <deepakkdalakoti@gmail.com>
License-File: LICENSE
Classifier: License :: OSI Approved :: MIT License
Classifier: Operating System :: OS Independent
Classifier: Programming Language :: Python :: 3
Requires-Python: >=3.10
